LICENSE
MANIFEST.in
README.md
requirements.txt
setup.py
cp2azure/__init__.py
cp2azure/app.py
cp2azure/azure.py
cp2azure/config.py
cp2azure.egg-info/PKG-INFO
cp2azure.egg-info/SOURCES.txt
cp2azure.egg-info/dependency_links.txt
cp2azure.egg-info/entry_points.txt
cp2azure.egg-info/requires.txt
cp2azure.egg-info/top_level.txt