Metadata-Version: 2.1
Name: cp2azure
Version: 1.3.0
Summary: COOPER to Azure IoT Hub
Home-page: https://github.com/hardwario/cp2azure
Author: HARDWARIO s.r.o.
Author-email: ask@hardwario.com
License: MIT
Keywords: cooper,azure,iot
Platform: UNKNOWN
Classifier: Development Status :: 5 - Production/Stable
Classifier: License :: OSI Approved :: MIT License
Classifier: Operating System :: OS Independent
Classifier: Programming Language :: Python
Classifier: Programming Language :: Python :: 3.5
Classifier: Programming Language :: Python :: 3.6
Classifier: Topic :: Scientific/Engineering :: Human Machine Interfaces
Classifier: Environment :: Console
Classifier: Intended Audience :: Science/Research
